{"window":{"fromYear":2022,"toYear":2024},"counts":{"openAlexSample":6000,"halSample":6000,"matched":2093,"openAlexOnly":3907,"halOnly":3907,"union":9907},"matchMethod":{"doi":2017,"fuzzyTitle":76},"rates":{"coverageByHal":0.34883333333333333,"coverageByOpenAlex":0.34883333333333333,"jaccardOfSets":0.2112647622892904},"typeComparison":[{"type":"Article","label":"Article","openAlex":4164,"hal":4599},{"type":"Preprint","label":"Preprint","openAlex":889,"hal":0},{"type":"ConferencePaper","label":"Communication","openAlex":0,"hal":617},{"type":"BookChapter","label":"Chapitre d'ouvrage","openAlex":403,"hal":171},{"type":"Book","label":"Ouvrage","openAlex":37,"hal":32},{"type":"Thesis","label":"Thèse / HDR","openAlex":128,"hal":467},{"type":"Report","label":"Rapport / Mémoire","openAlex":9,"hal":2},{"type":"Dataset","label":"Jeu de données","openAlex":127,"hal":0},{"type":"Other","label":"Autre","openAlex":243,"hal":112}],"examples":{"matched":[{"title":"Les « Carnets de notes des Mémoires d’Hadrien » : entre méthode historique et technique romanesque","doi":"10.4000/cei.10745","year":2022},{"title":"How many matchings cover the nodes of a graph?","doi":"10.1007/s10107-022-01804-9","year":2022},{"title":"Corrected Curvature Measures","doi":"10.1007/s00454-022-00399-4","year":2022},{"title":"Systoles and Lagrangians of random complex algebraic hypersurfaces","doi":"10.4171/jems/1208","year":2022},{"title":"La classe inversée. Les dessous d'un contrat","doi":"10.4000/ree.10079","year":2022},{"title":"The (non-)existence of perfect codes in Lucas cubes","doi":"10.26493/1855-3974.2308.de6","year":2022},{"title":"EQUIVARIANT COX RING","doi":"10.1007/s00031-022-09720-0","year":2022},{"title":"Enhancing sensitivity to rotations with quantum solitonic currents","doi":"10.21468/scipostphys.12.4.138","year":2022}],"openAlexOnly":[{"title":"Progress and Challenges in Intelligent Remote Sensing Satellite Systems","year":2022},{"title":"Rapid glacier retreat rates observed in West Antarctica","year":2022},{"title":"Many Labs 4: Failure to Replicate Mortality Salience Effect With and Without Original Author Involvement","year":2022},{"title":"Meta-analysis of epigenome-wide association studies in newborns and children show widespread sex differences in blood DNA methylation","year":2022},{"title":"Water management in anion-exchange membrane water electrolyzers under dry cathode operation","year":2022},{"title":"Predictor-based output feedback stabilization of an input delayed parabolic PDE with boundary measurement","year":2022}],"halOnly":[{"title":"The Institut de droit International’s response to the birth of the League of Nations","year":2024},{"title":"Pouvoir, le mot juste","year":2022},{"title":"Improved patterned media for probe-based HAMR","year":2022},{"title":"Counting what really counts? Assessing the political impact of science","year":2022},{"title":"Towards a new generation of Research Impact Assessment approaches","year":2022},{"title":"Detailed background dynamics and trans-planckian effects in loop quantum cosmology","year":2022}]},"internalSource":{"fileName":"publications.csv","records":1200,"recordsWithDoi":1199,"matchedToOpenAlex":1175,"coverage":0.9799833194328608}}